LICENSE
MANIFEST.in
README.md
setup.cfg
setup.py
image_to_midi/__init__.py
image_to_midi/image_to_midi.py
image_to_midi.egg-info/PKG-INFO
image_to_midi.egg-info/SOURCES.txt
image_to_midi.egg-info/dependency_links.txt
image_to_midi.egg-info/requires.txt
image_to_midi.egg-info/top_level.txt