Metadata-Version: 2.1
Name: image-to-midi
Version: 0.19
Summary: This is a python package that turns any images into MIDI files that views the same as them
Home-page: https://github.com/Rainbow-Dreamer/image_to_midi
Author: Rainbow-Dreamer
Author-email: 1036889495@qq.com
License: LGPLv2.1
Download-URL: https://github.com/Rainbow-Dreamer/image_to_midi/archive/0.19.tar.gz
Keywords: music,image,midi
Platform: UNKNOWN
Classifier: Development Status :: 3 - Alpha
Classifier: Intended Audience :: Developers
Classifier: Topic :: Software Development :: Build Tools
Classifier: License :: OSI Approved :: GNU Lesser General Public License v2 or later (LGPLv2+)
Classifier: Programming Language :: Python :: 3.6
Classifier: Programming Language :: Python :: 3.7
Classifier: Programming Language :: Python :: 3.8
Classifier: Programming Language :: Python :: 3.9
Classifier: Programming Language :: Python :: 3.10
